helicone_async/__init__.py
helicone_async/_constants.py
helicone_async/async_logger.py
helicone_async-1.1.1.dist-info/METADATA
helicone_async-1.1.1.dist-info/WHEEL
helicone_async-1.1.1.dist-info/RECORD
