Metadata-Version: 2.3
Name: helicone_async
Version: 1.1.1
Summary: A Python wrapper for logging llm traces directly to Helicone, by passing the proxy, with OpenLLMetry.
License: Apache-2.0
Author: Helicone, Inc.
Author-email: help@helicone.ai
Requires-Python: >=3.11.0,<4
Classifier: License :: OSI Approved :: Apache Software License
Classifier: Programming Language :: Python :: 3
Classifier: Programming Language :: Python :: 3.11
Classifier: Programming Language :: Python :: 3.12
Classifier: Programming Language :: Python :: 3.13
Requires-Dist: opentelemetry-exporter-otlp-proto-http (>=1.27.0,<2.0.0)
Requires-Dist: traceloop-sdk (>=0.33.1,<0.34.0)
Project-URL: Homepage, https://www.helicone.ai
Project-URL: Repository, https://github.com/helicone/helicone/helicone-python-async
